ham_tools/cli/__about__.py
ham_tools/cli/__init__.py
ham_tools/cli/__main__.py
ham_tools/__main__.py
ham_radio_tools-0.0.1a1.dist-info/METADATA
ham_radio_tools-0.0.1a1.dist-info/WHEEL
ham_radio_tools-0.0.1a1.dist-info/licenses/LICENSE
ham_radio_tools-0.0.1a1.dist-info/RECORD
