Metadata-Version: 2.3
Name: ham-radio-tools
Version: 0.0.1a1
Summary: A command-line interface for the ham_tools modules.
Project-URL: Documentation, https://github.com/afourney/ham-tools/README.md
Project-URL: Issues, https://github.com/afourney/ham-tools/issues
Project-URL: Source, https://github.com/afourney/ham-tools/
Author-email: Adam Fourney <adam.fourney@gmail.com>
License-Expression: MIT
License-File: LICENSE
Classifier: Development Status :: 4 - Beta
Classifier: Programming Language :: Python
Classifier: Programming Language :: Python :: 3.10
Classifier: Programming Language :: Python :: 3.11
Classifier: Programming Language :: Python :: 3.12
Classifier: Programming Language :: Python :: Implementation :: CPython
Classifier: Programming Language :: Python :: Implementation :: PyPy
Requires-Python: >=3.10
Requires-Dist: itu-prefixes
